LICENSE
README.rst
setup.py
mod_wsgi_metrics.egg-info/PKG-INFO
mod_wsgi_metrics.egg-info/SOURCES.txt
mod_wsgi_metrics.egg-info/dependency_links.txt
mod_wsgi_metrics.egg-info/requires.txt
mod_wsgi_metrics.egg-info/top_level.txt
src/__init__.py
src/metrics/__init__.py
src/metrics/sampler.py
src/metrics/scoreboard.py
src/metrics/statistics.py
src/metrics/newrelic/__init__.py
src/metrics/newrelic/agent.py
src/metrics/newrelic/platform.py